{
 "build_context_defines": [],
 "build_id": null,
 "build_mode": null,
 "build_source_pack": null,
 "conditional_fields": {},
 "constants": {},
 "created_at": null,
 "dependency_info": null,
 "dwarf": null,
 "dwarf_advanced": null,
 "elf": {
  "abi_flags": [],
  "bind_now": false,
  "e_flags": 0,
  "elf_class": 64,
  "gnu_properties": [],
  "has_dt_relr": false,
  "has_executable_stack": false,
  "has_fortify_source": false,
  "has_stack_canary": false,
  "has_static_tls": false,
  "has_tls_symbols": false,
  "has_writable_executable_segment": false,
  "hash_styles": [
   "gnu"
  ],
  "imports": [
   {
    "binding": "global",
    "is_default": true,
    "name": "__libc_start_main",
    "sym_type": "notype",
    "version": "GLIBC_2.28",
    "version_soname": "libc.so.6"
   },
   {
    "binding": "global",
    "is_default": true,
    "name": "memcpy",
    "sym_type": "notype",
    "version": "GLIBC_2.14",
    "version_soname": "libc.so.6"
   }
  ],
  "interpreter": "",
  "is_pie": false,
  "machine": "EM_X86_64",
  "needed": [
   "libc.so.6"
  ],
  "osabi": "ELFOSABI_SYSV",
  "pointer_size": 8,
  "relro": "none",
  "rpath": "",
  "runpath": "",
  "soname": "libdemo.so.1",
  "symbols": [
   {
    "binding": "global",
    "is_default": true,
    "name": "demo_init",
    "origin_lib": null,
    "size": 64,
    "sym_type": "func",
    "version": "",
    "visibility": "default"
   },
   {
    "binding": "global",
    "is_default": true,
    "name": "demo_process",
    "origin_lib": null,
    "size": 64,
    "sym_type": "func",
    "version": "",
    "visibility": "default"
   }
  ],
  "versions_defined": [],
  "versions_required": {
   "libc.so.6": [
    "GLIBC_2.17",
    "GLIBC_2.28"
   ]
  }
 },
 "elf_only_mode": true,
 "enums": [],
 "from_headers": false,
 "functions": [
  {
   "access": "public",
   "deleted_from_dwarf": false,
   "elf_visibility": null,
   "is_const": false,
   "is_deleted": false,
   "is_explicit": null,
   "is_extern_c": false,
   "is_hidden_friend": null,
   "is_inline": false,
   "is_noexcept": false,
   "is_pure_virtual": false,
   "is_static": false,
   "is_virtual": false,
   "is_volatile": false,
   "mangled": "demo_init",
   "name": "demo_init",
   "origin": "unknown",
   "params": [],
   "ref_qualifier": "",
   "return_pointer_depth": 0,
   "return_type": "int",
   "source_header": null,
   "source_location": null,
   "visibility": "public",
   "vtable_index": null
  },
  {
   "access": "public",
   "deleted_from_dwarf": false,
   "elf_visibility": null,
   "is_const": false,
   "is_deleted": false,
   "is_explicit": null,
   "is_extern_c": false,
   "is_hidden_friend": null,
   "is_inline": false,
   "is_noexcept": false,
   "is_pure_virtual": false,
   "is_static": false,
   "is_virtual": false,
   "is_volatile": false,
   "mangled": "demo_process",
   "name": "demo_process",
   "origin": "unknown",
   "params": [],
   "ref_qualifier": "",
   "return_pointer_depth": 0,
   "return_type": "int",
   "source_header": null,
   "source_location": null,
   "visibility": "public",
   "vtable_index": null
  }
 ],
 "git_commit": null,
 "git_tag": null,
 "kabi": null,
 "language_profile": null,
 "library": "libdemo.so.1",
 "macho": null,
 "parsed_with_build_context": false,
 "pe": null,
 "platform": "elf",
 "python_api": null,
 "python_ext": null,
 "schema_version": 8,
 "scope_fallback": null,
 "source_path": null,
 "sycl": null,
 "typedefs": {},
 "types": [],
 "variables": [],
 "version": "1.0"
}